agapi/__init__.py
agapi/cli.py
agapi/client.py
agapi/agents/__init__.py
agapi/agents/agent.py
agapi/agents/aliases.py
agapi/agents/client.py
agapi/agents/config.py
agapi/agents/functions.py
agapi/agents/schema.py
agapi/images/__init__.py
agapi-2025.12.25.dist-info/licenses/LICENSE
agapi-2025.12.25.dist-info/METADATA
agapi-2025.12.25.dist-info/WHEEL
agapi-2025.12.25.dist-info/top_level.txt
agapi-2025.12.25.dist-info/RECORD
