Metadata-Version: 2.4
Name: agapi
Version: 2025.12.25
Summary: agapi
Home-page: https://github.com/atomgptlab/agapi
Author: Kamal Choudhary
Author-email: kchoudh2@jhu.edu
Classifier: Programming Language :: Python :: 3
Classifier: License :: OSI Approved :: Apache Software License
Classifier: Operating System :: OS Independent
Requires-Python: >=3.10
License-File: LICENSE
Requires-Dist: numpy>=1.22.0
Requires-Dist: scipy>=1.6.3
Requires-Dist: jarvis-tools>=2021.07.19
Requires-Dist: openai-agents
Dynamic: author
Dynamic: author-email
Dynamic: classifier
Dynamic: description
Dynamic: description-content-type
Dynamic: home-page
Dynamic: license-file
Dynamic: requires-dist
Dynamic: requires-python
Dynamic: summary
